DocProfiler/docprofiler.py
docprofiler-1.0.1.dist-info/LICENSE
docprofiler-1.0.1.dist-info/METADATA
docprofiler-1.0.1.dist-info/WHEEL
docprofiler-1.0.1.dist-info/top_level.txt
docprofiler-1.0.1.dist-info/RECORD
