Metadata-Version: 2.1
Name: docprofiler
Version: 1.0.1
Summary: A Python package to generate document profiler or extract metadata from text in parallel using several Docker images
Home-page: https://github.com/Aayushpatel007/DocProfiler
Author: Aayush Patel
Author-email: patelaayush678@gmail.com
License: MIT
Platform: UNKNOWN
Classifier: License :: OSI Approved :: MIT License
Classifier: Programming Language :: Python :: 3
Classifier: Programming Language :: Python :: 3.5
Classifier: Programming Language :: Python :: 3.7
Classifier: Programming Language :: Python :: 3.8
Requires-Dist: aiohttp
Requires-Dist: asyncio
Requires-Dist: requests
